{
  "average_sentiment": 0.22,
  "time_taken": 35.37,
  "sentiments": {
    "98d34f1a": {
      "reasoning": "The article does not mention NVIDIA at all, it talks about copper prices and their impact on copper mining stocks Newmont and Freeport-McMoRan. Therefore, the sentiment towards the potential short-term stock value of NVIDIA is neutral.",
      "sentiment": 0.0,
      "confidence": 1.0,
      "valid": true,
      "url": "https://finance.yahoo.com/m/4c3284f6-3131-35db-9ceb-08a5d3abbeaa/copper-prices-have-surged-30%25.html?.tsrc=rss",
      "published": "Wed, 15 May 2024 20:05:19 +0000",
      "time_taken": 3.55
    },
    "ec88070b": {
      "reasoning": "The article reports a decrease in NVIDIA's shareholding by a hedge fund pioneer, which could be perceived as bearish news for the company's short-term stock value.",
      "sentiment": -0.43,
      "confidence": 0.85,
      "valid": true,
      "url": "https://finance.yahoo.com/news/paul-tudor-jones-adjusts-portfolio-200123123.html?.tsrc=rss",
      "published": "Wed, 15 May 2024 20:01:23 +0000",
      "time_taken": 2.89
    },
    "50e2881b": {
      "reasoning": "The article discusses Nvidia's shares climbing due to KeyBanc Capital Markets' limited signs of demand pause for the company, ahead of its first quarter earnings expected to top Wall Street estimates. The analysts see limited competitive risks and expect Nvidia to continue dominating one of the fastest-growing workloads in cloud and enterprise.",
      "sentiment": 0.83,
      "confidence": 0.92,
      "valid": true,
      "url": "https://finance.yahoo.com/video/nvidia-earnings-keybanc-capital-sees-194356782.html?.tsrc=rss",
      "published": "Wed, 15 May 2024 19:43:56 +0000",
      "time_taken": 5.02
    },
    "ce972942": {
      "reasoning": "The article mentions that Nvidia was part of the 'Magnificent Seven stocks' that had big gains in 2023, but then shows a divergence of returns in the early part of the second quarter of 2024. This implies that the sentiment towards Nvidia's potential short-term stock value is neutral.",
      "sentiment": 0.0,
      "confidence": 0.75,
      "valid": true,
      "url": "https://finance.yahoo.com/m/4205eaa9-f620-3a0b-a81a-0e82c7c9fd0b/magnificent-seven-stocks%3A.html?.tsrc=rss",
      "published": "Wed, 15 May 2024 19:22:42 +0000",
      "time_taken": 4.22
    },
    "30590623": {
      "reasoning": "The article mentions Nvidia's chipmaker Taiwan Semiconductor as one of the stocks highlighted in the IBD Screen Of The Day, which is a positive mention indicating potential growth or interest in the company.",
      "sentiment": 0.42,
      "confidence": 0.75,
      "valid": true,
      "url": "https://finance.yahoo.com/m/5a9a15d2-14ee-3633-b8a6-7244daefbf18/funds-keep-buying-nvidia%27s.html?.tsrc=rss",
      "published": "Wed, 15 May 2024 19:21:25 +0000",
      "time_taken": 3.0
    },
    "e53b79e1": {
      "reasoning": "The article suggests that Nvidia's stock value may not increase significantly unless it reports higher-than-expected revenue in its first quarter, implying a neutral sentiment towards the potential short-term stock value.",
      "sentiment": 0.0,
      "confidence": 0.8,
      "valid": true,
      "url": "https://finance.yahoo.com/m/78b76766-5929-3c73-9e80-9ad1393ed591/nvidia-stock-rises.-this-is.html?.tsrc=rss",
      "published": "Wed, 15 May 2024 18:58:00 +0000",
      "time_taken": 2.96
    },
    "d8ae9755": {
      "reasoning": "The article highlights that tech has been performing well in the stock market, but one of its benchmark ETFs is not reflecting this. The author suggests that investors are hesitant to invest in these tech stocks due to lower earnings growth compared to M7's forecasts.",
      "sentiment": -0.51,
      "confidence": 0.83,
      "valid": true,
      "url": "https://finance.yahoo.com/m/4eaf9074-d599-3691-b4f0-708f5d98b496/a-major-tech-etf-is-lagging..html?.tsrc=rss",
      "published": "Wed, 15 May 2024 18:53:00 +0000",
      "time_taken": 3.68
    },
    "edd5c12e": {
      "reasoning": "The article mentions a positive event for Nvidia, as Google's AI conference showcased an application that will improve search using artificial intelligence, which is closely related to Nvidia's products and services.",
      "sentiment": 0.73,
      "confidence": 0.85,
      "valid": true,
      "url": "https://finance.yahoo.com/m/dc591aa5-8656-399f-a2b0-90fb4c8c329e/nvidia-surges-after-google-ai.html?.tsrc=rss",
      "published": "Wed, 15 May 2024 17:39:22 +0000",
      "time_taken": 2.91
    }
  }
}